README
setup.py
src/SpiffGuard/Acl.py
src/SpiffGuard/Action.py
src/SpiffGuard/DB.py
src/SpiffGuard/DBObject.py
src/SpiffGuard/DBReader.py
src/SpiffGuard/Resource.py
src/SpiffGuard/ResourceGroup.py
src/SpiffGuard/ResourcePath.py
src/SpiffGuard/__init__.py
src/SpiffGuard/functions.py
src/SpiffGuard.egg-info/PKG-INFO
src/SpiffGuard.egg-info/SOURCES.txt
src/SpiffGuard.egg-info/dependency_links.txt
src/SpiffGuard.egg-info/requires.txt
src/SpiffGuard.egg-info/top_level.txt