Metadata-Version: 1.0
Name: SpiffGuard
Version: 1.9.2
Summary: A Generic Access List Library
Home-page: http://code.google.com/p/spiff-guard/
Author: Samuel Abels
Author-email: cheeseshop.python.org@debain.org
License: GPLv2
Keywords: spiff guard acl acls security authentication object storage
Platform: UNKNOWN
Classifier: Development Status :: 5 - Production/Stable
Classifier: Intended Audience :: Developers
Classifier: License :: OSI Approved :: GNU General Public License (GPL)
Classifier: Programming Language :: Python
Classifier: Topic :: Security
Classifier: Topic :: Software Development :: Libraries
Classifier: Topic :: Software Development :: Libraries :: Python Modules
